galaxy/perfo/__init__.py
galaxy/perfo/decorator.py
galaxy_py_perfo-0.0.2.dist-info/AUTHORS
galaxy_py_perfo-0.0.2.dist-info/COPYING.md
galaxy_py_perfo-0.0.2.dist-info/LICENSE.txt
galaxy_py_perfo-0.0.2.dist-info/METADATA
galaxy_py_perfo-0.0.2.dist-info/WHEEL
galaxy_py_perfo-0.0.2.dist-info/RECORD
